{"updatedAt":"2026-04-22T23:48:33.987Z","rankThreshold":5,"stakeThresholdTX":500000,"arrivals":[],"exits":[],"rankMovers":[{"address":"core150nt4mrjpycwudsw9syp0mz4qhxuar7k9zjsmq","label":null,"previousRank":371,"currentRank":214,"rankDelta":157,"totalStake":1115698},{"address":"core1d4ywdzz84t8mzhe4lyu2q69v8eq7msmcrgumtm","label":null,"previousRank":209,"currentRank":192,"rankDelta":17,"totalStake":1224102},{"address":"core1aggtef90mx39uyhpasy0javcdtml4fj4rlgev5","label":null,"previousRank":22,"currentRank":8,"rankDelta":14,"totalStake":9045947}],"stakeMovers":[{"address":"core1aggtef90mx39uyhpasy0javcdtml4fj4rlgev5","label":null,"previousStake":5173859,"currentStake":9045947,"stakeDelta":3872088,"currentRank":8}]}